_ccronexpr.cpython-38-darwin.so
cronexpr-0.30.0.dist-info/RECORD
cronexpr-0.30.0.dist-info/WHEEL
cronexpr-0.30.0.dist-info/METADATA
cronexpr-0.30.0.dist-info/licenses/LICENSE.txt
cronexpr/__init__.py
