Metadata-Version: 2.1
Name: cronexpr
Version: 0.30.0
Summary: Python bindings for cronexpr using supertinycron
License: Apache-2.0
Project-URL: Homepage, https://github.com/CodyRay/pycronexpr
Project-URL: Bug tracker, https://github.com/CodyRay/pycronexpr/issues
Project-URL: Changelog, https://github.com/CodyRay/pycronexpr/releases
Requires-Python: >=3.8
